README.md
setup.py
./lemon/__init__.py
lemonmarkets.egg-info/PKG-INFO
lemonmarkets.egg-info/SOURCES.txt
lemonmarkets.egg-info/dependency_links.txt
lemonmarkets.egg-info/top_level.txt