Metadata-Version: 2.1
Name: lemonmarkets
Version: 0.0.0
Summary: SDK for lemon.markets API
Home-page: http://lemon.markets
Author: lemon.markets
Author-email: cto@lemon.markets
License: UNKNOWN
Platform: UNKNOWN
